upas/__init__.py
upas/analyzer.py
upas/api.py
upas/cli.py
upas/protocols.py
upas/replay.py
upas/analysis/__init__.py
upas/analysis/behavior.py
upas/analysis/parser.py
upas/analysis/pattern.py
upas/analysis/similarity.py
upas/analysis/upas_generator.py
upas/api/__init__.py
upas/api/high_level.py
upas/api/manager.py
upas/api/utils.py
upas/core/__init__.py
upas/core/behavior.py
upas/core/engine.py
upas/core/packet.py
upas/core/state.py
upas/core/transport.py
upas/core/behavior/__init__.py
upas/core/behavior/base.py
upas/core/behavior/executor.py
upas/core/behavior/responses.py
upas/core/behavior/state_behaviors.py
upas/core/behavior/payload/__init__.py
upas/core/behavior/payload/builder.py
upas/core/behavior/payload/counters.py
upas/core/behavior/payload/patterns.py
upas/core/behavior/payload/variables.py
upas/core/behavior/scheduling/__init__.py
upas/core/behavior/scheduling/scheduler.py
upas/core/behavior/scheduling/timing.py
upas/core/behavior/state/__init__.py
upas/core/behavior/state/context.py
upas/core/behavior/types/__init__.py
upas/core/behavior/types/periodic.py
upas/core/behavior/types/reactive.py
upas/core/behavior/types/triggered.py
upas/core/transport/__init__.py
upas/core/transport/base.py
upas/core/transport/layer.py
upas/core/transport/ethernet/__init__.py
upas/core/transport/ethernet/ip_options.py
upas/core/transport/ethernet/tcp_service.py
upas/core/transport/ethernet/transport.py
upas/core/transport/ethernet/udp_service.py
upas/core/transport/raw/__init__.py
upas/core/transport/raw/transport.py
upas/core/transport/utils/__init__.py
upas/core/transport/utils/address_parser.py
upas/core/transport/utils/socket_helpers.py
upas-1.0.15.dist-info/licenses/LICENSE
upas-1.0.15.dist-info/METADATA
upas-1.0.15.dist-info/WHEEL
upas-1.0.15.dist-info/entry_points.txt
upas-1.0.15.dist-info/top_level.txt
upas-1.0.15.dist-info/RECORD
