Metadata-Version: 2.4
Name: upas
Version: 1.0.15
Summary: Universal Protocol Analysis & Simulation Framework
Home-page: https://github.com/BitsDiver/upas-cli
Author: BitsDiver Team
Author-email: BitsDiver Team <contact@bitsdiver.com>
License: MIT
Project-URL: Homepage, https://github.com/BitsDiver/upas-cli
Project-URL: Documentation, https://github.com/BitsDiver/upas-cli/blob/main/docs/SPECIFICATIONS.md
Project-URL: Repository, https://github.com/BitsDiver/upas-cli
Project-URL: Bug Tracker, https://github.com/BitsDiver/upas-cli/issues
Project-URL: Changelog, https://github.com/BitsDiver/upas-cli/blob/main/MIGRATION_COMPLETE.md
Keywords: protocol analysis,network simulation,reverse engineering,iot security,network testing,packet analysis,protocol simulation,industrial protocols
Classifier: Development Status :: 5 - Production/Stable
Classifier: Intended Audience :: Developers
Classifier: Intended Audience :: Science/Research
Classifier: Intended Audience :: System Administrators
Classifier: Intended Audience :: Telecommunications Industry
Classifier: License :: OSI Approved :: MIT License
Classifier: Operating System :: OS Independent
Classifier: Programming Language :: Python :: 3
Classifier: Programming Language :: Python :: 3.7
Classifier: Programming Language :: Python :: 3.8
Classifier: Programming Language :: Python :: 3.9
Classifier: Programming Language :: Python :: 3.10
Classifier: Programming Language :: Python :: 3.11
Classifier: Programming Language :: Python :: 3.12
Classifier: Topic :: System :: Networking
Classifier: Topic :: Software Development :: Libraries :: Python Modules
Classifier: Topic :: Scientific/Engineering
Classifier: Topic :: Security
Classifier: Topic :: System :: Systems Administration
Requires-Python: >=3.7
License-File: LICENSE
Provides-Extra: dev
Requires-Dist: pytest>=6.0; extra == "dev"
Requires-Dist: pytest-cov>=2.10.0; extra == "dev"
Requires-Dist: pytest-asyncio>=0.18.0; extra == "dev"
Requires-Dist: black>=24.10.0; extra == "dev"
Requires-Dist: isort>=5.0.0; extra == "dev"
Requires-Dist: pylint>=2.10.0; extra == "dev"
Requires-Dist: mypy>=0.910; extra == "dev"
Requires-Dist: flake8>=3.9.0; extra == "dev"
Requires-Dist: pre-commit>=2.15.0; extra == "dev"
Provides-Extra: analysis
Requires-Dist: scapy>=2.4.0; extra == "analysis"
Provides-Extra: networking
Requires-Dist: netifaces>=0.11.0; extra == "networking"
Provides-Extra: iot
Requires-Dist: asyncio-mqtt>=0.10.0; extra == "iot"
Requires-Dist: pyserial>=3.5; extra == "iot"
Provides-Extra: cli
Requires-Dist: click>=7.0; extra == "cli"
Requires-Dist: colorama>=0.4.0; extra == "cli"
Provides-Extra: full
Requires-Dist: scapy>=2.4.0; extra == "full"
Requires-Dist: netifaces>=0.11.0; extra == "full"
Requires-Dist: asyncio-mqtt>=0.10.0; extra == "full"
Requires-Dist: pyserial>=3.5; extra == "full"
Requires-Dist: click>=7.0; extra == "full"
Requires-Dist: colorama>=0.4.0; extra == "full"
Dynamic: author
Dynamic: home-page
Dynamic: license-file
Dynamic: requires-python
